[
  {
    "ContainingType": "WebApi.Controllers.BookingController",
    "Method": "BookSeat",
    "RelativePath": "api/Booking/book-seat",
    "HttpMethod": "POST",
    "IsController": true,
    "Order": 0,
    "Parameters": [
      {
        "Name": "input",
        "Type": "Application.Contracts.DTOs.BookSeatInputDto",
        "IsRequired": true
      }
    ],
    "ReturnTypes": []
  },
  {
    "ContainingType": "WebApi.Controllers.BookingController",
    "Method": "GetSeatPlan",
    "RelativePath": "api/Booking/seat-plan/{busScheduleId}",
    "HttpMethod": "GET",
    "IsController": true,
    "Order": 0,
    "Parameters": [
      {
        "Name": "busScheduleId",
        "Type": "System.Guid",
        "IsRequired": true
      }
    ],
    "ReturnTypes": []
  },
  {
    "ContainingType": "WebApi.Controllers.SearchController",
    "Method": "GetAvailableBuses",
    "RelativePath": "api/Search/available-buses",
    "HttpMethod": "GET",
    "IsController": true,
    "Order": 0,
    "Parameters": [
      {
        "Name": "from",
        "Type": "System.String",
        "IsRequired": false
      },
      {
        "Name": "to",
        "Type": "System.String",
        "IsRequired": false
      },
      {
        "Name": "journeyDate",
        "Type": "System.DateTime",
        "IsRequired": false
      }
    ],
    "ReturnTypes": []
  }
]